evoagent/__init__.py
evoagent/agent/agent.py
evoagent/cool_stuff/podcast.py
evoagent/cool_stuff/visualizer.py
evoagent/embeddings/__init__.py
evoagent/embeddings/openai_embeddings.py
evoagent/embeddings/sentence_transformers_embeddings.py
evoagent/llms/llms.py
evoagent/phidata/finance_agent.py
evoagent/phidata/web_agent.py
evoagent/streamlit/__init__.py
evoagent/streamlit/base_chatbot.py
evoagent/streamlit/pdf_chatbot.py
evoagent/streamlit/vision_chatbot.py
evoagent/stt/stt.py
evoagent/tools/crawl4ai.py
evoagent/tools/docling.py
evoagent/tools/file_reader.py
evoagent/vector_stores/__init__.py
evoagent/vector_stores/qdrant.py
evoagent-0.0.4.dist-info/METADATA
evoagent-0.0.4.dist-info/WHEEL
evoagent-0.0.4.dist-info/top_level.txt
evoagent-0.0.4.dist-info/RECORD
