Metadata-Version: 2.2
Name: evoagent
Version: 0.0.4
Summary: An orchestration framework for evolving autonomous AI agents
Home-page: https://github.com/bharath4ru/evoagent
Author: Munakala Bharath
Author-email: bharathmunakala22@gmail.com
Requires-Python: >=3.10
Requires-Dist: openai
Requires-Dist: anthropic
Requires-Dist: groq
Requires-Dist: python-dotenv
Requires-Dist: qdrant-client
Requires-Dist: requests
Requires-Dist: PyPDF2
Requires-Dist: python-docx
Requires-Dist: soundfile
Requires-Dist: tiktoken
Requires-Dist: faiss-cpu
Requires-Dist: pydantic
Requires-Dist: fastapi
Requires-Dist: uvicorn
Requires-Dist: pymupdf
Requires-Dist: pandas
Requires-Dist: numpy
Requires-Dist: matplotlib
Requires-Dist: langchain
Requires-Dist: llama-index
Requires-Dist: chainlit
Requires-Dist: phidata
Requires-Dist: huggingface_hub
Dynamic: author
Dynamic: author-email
Dynamic: home-page
Dynamic: requires-python
